cm107_package_test/__init__.py
cm107_package_test/lib/__init__.py
cm107_package_test/util/__init__.py
cm107_package_test/util/messages.py
cm107_package_test/util/test.py
cm107_package_test-0.2.dist-info/LICENSE
cm107_package_test-0.2.dist-info/METADATA
cm107_package_test-0.2.dist-info/WHEEL
cm107_package_test-0.2.dist-info/top_level.txt
cm107_package_test-0.2.dist-info/RECORD
